Workbook

Sheet INDICADORES
F2: GERENCIADOR FINANCEIRO | Q2: Código
Q3: R.PD.023
Q4: Revisão
Q5: 2.0
Q6: Data
Q7: 45513
Q8: Página
Q9: INDICADORES / R.PD.023
B11: FLUXO DE CAIXA | N11: EMPRESA | S11: ANO
N12: Cliente | S12: 2025
C14: SALDO | D14: RESULTADO
F15: JAN | G15: FEV | H15: MAR | I15: ABR | J15: MAI | K15: JUN | L15: JUL | M15: AGO | N15: SET | O15: OUT | P15: NOV | Q15: DEZ | S15: TOTAL
D16: LUCRO ESTIMADO | F16: =F38-F71 -> 0 | G16: =G38-G71 -> 0 | H16: =H38-H71 -> 0 | I16: =I38-I71 -> 0 | J16: =J38-J71 -> 0 | K16: =K38-K71 -> 0 | L16: =L38-L71 -> 0 | M16: =M38-M71 -> 0 | ... Q16: =Q38-Q71 -> 0 | S16: =SUM(F16:Q16) -> 0
D17: LUCRO OBTIDO | F17: =F39-F72 -> 0 | G17: =G39-G72 -> 0 | H17: =H39-H72 -> 0 | I17: =I39-I72 -> 0 | J17: =J39-J72 -> 0 | K17: =K39-K72 -> 0 | L17: =L39-L72 -> 0 | M17: =M39-M72 -> 0 | ... Q17: =Q39-Q72 -> 0 | S17: =SUM(F17:Q17) -> 0
D18: % LUCRATIVIDADE | F18: =IFERROR(F17/F39,"-") -> - | G18: =IFERROR(G17/G39,"-") -> - | H18: =IFERROR(H17/H39,"-") -> - | I18: =IFERROR(I17/I39,"-") -> - | J18: =IFERROR(J17/J39,"-") -> - | K18: =IFERROR(K17/K39,"-") -> - | L18: =IFERROR(L17/L39,"-") -> - | M18: =IFERROR(M17/M39,"-") -> - | ... Q18: =IFERROR(Q17/Q39,"-") -> - | S18: =IFERROR(AVERAGE(F18:Q18),"-") -> -
F19: =F17-F16 -> 0 | G19: =G17-G16 -> 0 | H19: =H17-H16 -> 0 | I19: =I17-I16 -> 0 | J19: =J17-J16 -> 0 | K19: =K17-K16 -> 0 | L19: =L17-L16 -> 0 | M19: =M17-M16 -> 0 | ... Q19: =Q17-Q16 -> 0 | S19: =S17-S16 -> 0
C36: ENTRADAS | D36: RECEITAS
F37: JAN | G37: FEV | H37: MAR | I37: ABR | J37: MAI | K37: JUN | L37: JUL | M37: AGO | N37: SET | O37: OUT | P37: NOV | Q37: DEZ | S37: TOTAL
D38: PREVISTO | F38: =RECEITAS!D16 -> 0 | G38: =RECEITAS!F16 -> 0 | H38: =RECEITAS!H16 -> 0 | I38: =RECEITAS!J16 -> 0 | J38: =RECEITAS!L16 -> 0 | K38: =RECEITAS!N16 -> 0 | L38: =RECEITAS!P16 -> 0 | M38: =RECEITAS!R16 -> 0 | N38: =RECEITAS!T16 -> 0 | O38: =RECEITAS!V16 -> 0 | P38: =RECEITAS!X16 -> 0 | Q38: =RECEITAS!Z16 -> 0 | S38: =SUM(F38:Q38) -> 0
D39: REALIZADO | F39: =RECEITAS!E16 -> 0 | G39: =RECEITAS!G16 -> 0 | H39: =RECEITAS!I16 -> 0 | I39: =RECEITAS!K16 -> 0 | J39: =RECEITAS!M16 -> 0 | K39: =RECEITAS!O16 -> 0 | L39: =RECEITAS!Q16 -> 0 | M39: =RECEITAS!S16 -> 0 | N39: =RECEITAS!U16 -> 0 | O39: =RECEITAS!W16 -> 0 | P39: =RECEITAS!Y16 -> 0 | Q39: =RECEITAS!AA16 -> 0 | S39: =SUM(F39:Q39) -> 0
G57: JAN | H57: FEV | I57: MAR | J57: ABR | K57: MAI | L57: JUN | M57: JUL | N57: AGO | O57: SET | P57: OUT | Q57: NOV | R57: DEZ
F58: =RECEITAS!C18 -> PRODUTOS/SERVIÇOS | G58: =RECEITAS!E22 -> 0 | H58: =RECEITAS!G22 -> 0 | I58: =RECEITAS!I22 -> 0 | J58: =RECEITAS!K22 -> 0 | K58: =RECEITAS!M22 -> 0 | L58: =RECEITAS!O22 -> 0 | M58: =RECEITAS!Q22 -> 0 | N58: =RECEITAS!S22 -> 0 | O58: =RECEITAS!U22 -> 0 | P58: =RECEITAS!W22 -> 0 | Q58: =RECEITAS!Y22 -> 0 | R58: =RECEITAS!AA22 -> 0
F59: =RECEITAS!C51 -> OUTRAS RECEITAS | G59: =RECEITAS!E55 -> 0 | H59: =RECEITAS!G55 -> 0 | I59: =RECEITAS!I55 -> 0 | J59: =RECEITAS!K55 -> 0 | K59: =RECEITAS!M55 -> 0 | L59: =RECEITAS!O55 -> 0 | M59: =RECEITAS!Q55 -> 0 | N59: =RECEITAS!S55 -> 0 | O59: =RECEITAS!U55 -> 0 | P59: =RECEITAS!W55 -> 0 | Q59: =RECEITAS!Y55 -> 0 | R59: =RECEITAS!AA55 -> 0
F60: =RECEITAS!C71 -> RECEITAS FINANCEIRAS | G60: =RECEITAS!E75 -> 0 | H60: =RECEITAS!G75 -> 0 | I60: =RECEITAS!I75 -> 0 | J60: =RECEITAS!K75 -> 0 | K60: =RECEITAS!M75 -> 0 | L60: =RECEITAS!O75 -> 0 | M60: =RECEITAS!Q75 -> 0 | N60: =RECEITAS!S75 -> 0 | O60: =RECEITAS!U75 -> 0 | P60: =RECEITAS!W75 -> 0 | Q60: =RECEITAS!Y75 -> 0 | R60: =RECEITAS!AA75 -> 0
F64: =G57 -> JAN | G64: =H57 -> FEV | H64: =I57 -> MAR | I64: =J57 -> ABR | J64: =K57 -> MAI | K64: =L57 -> JUN | L64: =M57 -> JUL | M64: =N57 -> AGO | ... Q64: =R57 -> DEZ | S64: TOTAL
D65: =F58 -> PRODUTOS/SERVIÇOS | F65: =G58 -> 0 | G65: =H58 -> 0 | H65: =I58 -> 0 | I65: =J58 -> 0 | J65: =K58 -> 0 | K65: =L58 -> 0 | L65: =M58 -> 0 | M65: =N58 -> 0 | ... Q65: =R58 -> 0 | S65: =SUM(F65:Q65) -> 0
D66: =F59 -> OUTRAS RECEITAS | F66: =G59 -> 0 | G66: =H59 -> 0 | H66: =I59 -> 0 | I66: =J59 -> 0 | J66: =K59 -> 0 | K66: =L59 -> 0 | L66: =M59 -> 0 | M66: =N59 -> 0 | ... Q66: =R59 -> 0 | S66: =SUM(F66:Q66) -> 0
D67: =F60 -> RECEITAS FINANCEIRAS | F67: =G60 -> 0 | G67: =H60 -> 0 | H67: =I60 -> 0 | I67: =J60 -> 0 | J67: =K60 -> 0 | K67: =L60 -> 0 | L67: =M60 -> 0 | M67: =N60 -> 0 | ... Q67: =R60 -> 0 | S67: =SUM(F67:Q67) -> 0
C69: SAÍDAS | D69: GASTOS
F70: JAN | G70: FEV | H70: MAR | I70: ABR | J70: MAI | K70: JUN | L70: JUL | M70: AGO | N70: SET | O70: OUT | P70: NOV | Q70: DEZ | S70: TOTAL
D71: PREVISTO | F71: =GASTOS!E16 -> 0 | G71: =GASTOS!G16 -> 0 | H71: =GASTOS!I16 -> 0 | I71: =GASTOS!K16 -> 0 | J71: =GASTOS!M16 -> 0 | K71: =GASTOS!O16 -> 0 | L71: =GASTOS!Q16 -> 0 | M71: =GASTOS!S16 -> 0 | N71: =GASTOS!U16 -> 0 | O71: =GASTOS!W16 -> 0 | P71: =GASTOS!Y16 -> 0 | Q71: =GASTOS!AA16 -> 0 | S71: =SUM(F71:Q71) -> 0
D72: REALIZADO | F72: =GASTOS!F16 -> 0 | G72: =GASTOS!H16 -> 0 | H72: =GASTOS!J16 -> 0 | I72: =GASTOS!L16 -> 0 | J72: =GASTOS!N16 -> 0 | K72: =GASTOS!P16 -> 0 | L72: =GASTOS!R16 -> 0 | M72: =GASTOS!T16 -> 0 | N72: =GASTOS!V16 -> 0 | O72: =GASTOS!X16 -> 0 | P72: =GASTOS!Z16 -> 0 | Q72: =GASTOS!AB16 -> 0 | S72: =SUM(F72:Q72) -> 0
G89: JAN | H89: FEV | I89: MAR | J89: ABR | K89: MAI | L89: JUN | M89: JUL | N89: AGO | O89: SET | P89: OUT | Q89: NOV | R89: DEZ
F90: =GASTOS!C18 -> DESPESAS OPERACIONAIS | G90: =GASTOS!F22 -> 0 | H90: =GASTOS!H22 -> 0 | I90: =GASTOS!J22 -> 0 | J90: =GASTOS!L22 -> 0 | K90: =GASTOS!N22 -> 0 | L90: =GASTOS!P22 -> 0 | M90: =GASTOS!R22 -> 0 | N90: =GASTOS!T22 -> 0 | O90: =GASTOS!V22 -> 0 | P90: =GASTOS!X22 -> 0 | Q90: =GASTOS!Z22 -> 0 | R90: =GASTOS!AB22 -> 0
F91: =GASTOS!C84 -> CUSTOS PRODUTOS/SERVIÇOS | G91: =GASTOS!F88 -> 0 | H91: =GASTOS!H88 -> 0 | I91: =GASTOS!J88 -> 0 | J91: =GASTOS!L88 -> 0 | K91: =GASTOS!N88 -> 0 | L91: =GASTOS!P88 -> 0 | M91: =GASTOS!R88 -> 0 | N91: =GASTOS!T88 -> 0 | O91: =GASTOS!V88 -> 0 | P91: =GASTOS!X88 -> 0 | Q91: =GASTOS!Z88 -> 0 | R91: =GASTOS!AB88 -> 0
F92: =GASTOS!C110 -> IMPOSTOS E TAXAS | G92: =GASTOS!F114 -> 0 | H92: =GASTOS!H114 -> 0 | I92: =GASTOS!J114 -> 0 | J92: =GASTOS!L114 -> 0 | K92: =GASTOS!N114 -> 0 | L92: =GASTOS!P114 -> 0 | M92: =GASTOS!R114 -> 0 | N92: =GASTOS!T114 -> 0 | O92: =GASTOS!V114 -> 0 | P92: =GASTOS!X114 -> 0 | Q92: =GASTOS!Z114 -> 0 | R92: =GASTOS!AB114 -> 0
F93: =GASTOS!C141 -> INVESTIMENTOS | G93: =GASTOS!F145 -> 0 | H93: =GASTOS!H145 -> 0 | I93: =GASTOS!J145 -> 0 | J93: =GASTOS!L145 -> 0 | K93: =GASTOS!N145 -> 0 | L93: =GASTOS!P145 -> 0 | M93: =GASTOS!R145 -> 0 | N93: =GASTOS!T145 -> 0 | O93: =GASTOS!V145 -> 0 | P93: =GASTOS!X145 -> 0 | Q93: =GASTOS!Z145 -> 0 | R93: =GASTOS!AB145 -> 0
F97: JAN | G97: FEV | H97: MAR | I97: ABR | J97: MAI | K97: JUN | L97: JUL | M97: AGO | N97: SET | O97: OUT | P97: NOV | Q97: DEZ | S97: TOTAL
D98: DESP. OPERACIONAIS | F98: =G90 -> 0 | G98: =H90 -> 0 | H98: =I90 -> 0 | I98: =J90 -> 0 | J98: =K90 -> 0 | K98: =L90 -> 0 | L98: =M90 -> 0 | M98: =N90 -> 0 | ... Q98: =R90 -> 0 | S98: =SUM(F98:Q98) -> 0
D99: CUSTO PROD. / SERV. | F99: =G91 -> 0 | G99: =H91 -> 0 | H99: =I91 -> 0 | I99: =J91 -> 0 | J99: =K91 -> 0 | K99: =L91 -> 0 | L99: =M91 -> 0 | M99: =N91 -> 0 | ... Q99: =R91 -> 0 | S99: =SUM(F99:Q99) -> 0
D100: =F92 -> IMPOSTOS E TAXAS | F100: =G92 -> 0 | G100: =H92 -> 0 | H100: =I92 -> 0 | I100: =J92 -> 0 | J100: =K92 -> 0 | K100: =L92 -> 0 | L100: =M92 -> 0 | M100: =N92 -> 0 | ... Q100: =R92 -> 0 | S100: =SUM(F100:Q100) -> 0
D101: =F93 -> INVESTIMENTOS | F101: =G93 -> 0 | G101: =H93 -> 0 | H101: =I93 -> 0 | I101: =J93 -> 0 | J101: =K93 -> 0 | K101: =L93 -> 0 | L101: =M93 -> 0 | M101: =N93 -> 0 | ... Q101: =R93 -> 0 | S101: =SUM(F101:Q101) -> 0
E104: Esta obra está licenciada com uma Licença Creative Commons Atribuição-NãoComercial 4.0 Internacional.

Sheet CADASTRO DE ITENS
E3: REGISTRO FINANCEIRO MENSAL | W3: Código
W4: R.OP.007
W5: Revisão
W6: 1.0
W7: Data
W8: 45763
W9: Página
W10: CADASTRO DE ITENS / R.OP.007
C12: CADASTRO DE ITENS
C15: NOME DO ITEM: | D15: RECEITAS | Produtos e Serviços | F15: NOME DO ITEM: | G15: RECEITAS | Outras Receitas | I15: NOME DO ITEM: | K15: RECEITAS | Receitas Financeiras | M15: NOME DO ITEM: | N15: GASTOS | Despesas Operacionais | P15: NOME DO ITEM: | Q15: GASTOS | Custos de Produtos e Serviços | S15: NOME DO ITEM: | T15: GASTOS | Impostos e Taxas | V15: NOME DO ITEM: | W15: GASTOS | Investimentos
C16: LISTAGEM | F16: LISTAGEM | I16: LISTAGEM | J16: =_xlfn.CONCAT(K16,#REF!) -> #REF! | M16: LISTAGEM | P16: LISTAGEM | S16: LISTAGEM | V16: LISTAGEM
J17: =_xlfn.CONCAT(K17,#REF!) -> #REF!
J18: =_xlfn.CONCAT(K18,#REF!) -> #REF!
J19: =_xlfn.CONCAT(K19,#REF!) -> #REF!
J20: =_xlfn.CONCAT(K20,#REF!) -> #REF!
J21: =_xlfn.CONCAT(K21,#REF!) -> #REF!
J22: =_xlfn.CONCAT(K22,#REF!) -> #REF!
J23: =_xlfn.CONCAT(K23,#REF!) -> #REF!
J24: =_xlfn.CONCAT(K24,#REF!) -> #REF!
J25: =_xlfn.CONCAT(K25,#REF!) -> #REF!
J26: =_xlfn.CONCAT(K26,#REF!) -> #REF!
J27: =_xlfn.CONCAT(K27,#REF!) -> #REF!
J28: =_xlfn.CONCAT(K28,#REF!) -> #REF!
... J31: =_xlfn.CONCAT(K31,#REF!) -> #REF!
D32: =IF([1]BaseSafra!E367="","",[1]BaseSafra!E367) | J32: =_xlfn.CONCAT(K32,#REF!) -> #REF!
D33: =IF([1]BaseSafra!E389="","",[1]BaseSafra!E389) | J33: =_xlfn.CONCAT(K33,#REF!) -> #REF!
D34: =IF([1]BaseSafra!E411="","",[1]BaseSafra!E411) | J34: =_xlfn.CONCAT(K34,#REF!) -> #REF!
D35: =IF([1]BaseSafra!E433="","",[1]BaseSafra!E433) | J35: =_xlfn.CONCAT(K35,#REF!) -> #REF!
D36: =IF([1]BaseSafra!E455="","",[1]BaseSafra!E455) | J36: =_xlfn.CONCAT(K36,#REF!) -> #REF!
D37: =IF([1]BaseSafra!E477="","",[1]BaseSafra!E477) | J37: =_xlfn.CONCAT(K37,#REF!) -> #REF!
D38: =IF([1]BaseSafra!E499="","",[1]BaseSafra!E499)
D39: =IF([1]BaseSafra!E521="","",[1]BaseSafra!E521)
D40: =IF([1]BaseSafra!E543="","",[1]BaseSafra!E543)
D41: =IF([1]BaseSafra!E565="","",[1]BaseSafra!E565)
D42: =IF([1]BaseSafra!E587="","",[1]BaseSafra!E587)
D43: =IF([1]BaseSafra!E609="","",[1]BaseSafra!E609)
D44: =IF([1]BaseSafra!E631="","",[1]BaseSafra!E631)
C146: Esta obra está licenciada com uma Licença Creative Commons Atribuição-NãoComercial 4.0 Internacional.

Sheet RECEITAS
D2: REGISTRO FINANCEIRO MENSAL | AA2: Código
AA3: R.OP.007
AA4: Revisão
AA5: 1.0
AA6: Data
AA7: 45763
AA8: Página
AA9: RECEITAS / R.OP.007
C12: RECEITAS
D14: JAN | F14: FEV | H14: MAR | J14: ABR | L14: MAI | N14: JUN | P14: JUL | R14: AGO | T14: SET | V14: OUT | X14: NOV | Z14: DEZ | AC14: SOMATÓRIO
D15: PREVISTO | E15: REALIZADO | F15: PREVISTO | G15: REALIZADO | H15: PREVISTO | I15: REALIZADO | J15: PREVISTO | K15: REALIZADO | L15: PREVISTO | M15: REALIZADO | N15: PREVISTO | O15: REALIZADO | P15: PREVISTO | Q15: REALIZADO | R15: PREVISTO | S15: REALIZADO | T15: PREVISTO | U15: REALIZADO | V15: PREVISTO | W15: REALIZADO | X15: PREVISTO | Y15: REALIZADO | Z15: PREVISTO | AA15: REALIZADO | AC15: PREVISTO | AD15: REALIZADO
C16: TOTAL MENSAL | D16: =IFERROR(SUM(D22,D55,D75),0) -> 0 | E16: =IFERROR(SUM(E22,E55,E75),0) -> 0 | F16: =IFERROR(SUM(F22,F55,F75),0) -> 0 | G16: =IFERROR(SUM(G22,G55,G75),0) -> 0 | H16: =IFERROR(SUM(H22,H55,H75),0) -> 0 | I16: =IFERROR(SUM(I22,I55,I75),0) -> 0 | J16: =IFERROR(SUM(J22,J55,J75),0) -> 0 | K16: =IFERROR(SUM(K22,K55,K75),0) -> 0 | ... AA16: =IFERROR(SUM(AA22,AA55,AA75),0) -> 0 | AC16: =IFERROR(SUM(D16,F16,H16,J16,L16,N16,P16,R16,T16,V16,X16,Z16),0) -> 0 | AD16: =IFERROR(SUM(E16,G16,I16,K16,M16,O16,Q16,S16,U16,W16,Y16,AA16),0) -> 0
C18: PRODUTOS/SERVIÇOS
C20: DESCRIÇÃO | D20: JAN | F20: FEV | H20: MAR | J20: ABR | L20: MAI | N20: JUN | P20: JUL | R20: AGO | T20: SET | V20: OUT | X20: NOV | Z20: DEZ | AC20: SOMATÓRIO
D21: PREVISTO | E21: REALIZADO | F21: PREVISTO | G21: REALIZADO | H21: PREVISTO | I21: REALIZADO | J21: PREVISTO | K21: REALIZADO | L21: PREVISTO | M21: REALIZADO | N21: PREVISTO | O21: REALIZADO | P21: PREVISTO | Q21: REALIZADO | R21: PREVISTO | S21: REALIZADO | T21: PREVISTO | U21: REALIZADO | V21: PREVISTO | W21: REALIZADO | X21: PREVISTO | Y21: REALIZADO | Z21: PREVISTO | AA21: REALIZADO | AC21: PREVISTO | AD21: REALIZADO
D22: =IFERROR(SUM(D23:D49),0) -> 0 | E22: =IFERROR(SUM(E23:E49),0) -> 0 | F22: =IFERROR(SUM(F23:F49),0) -> 0 | G22: =IFERROR(SUM(G23:G49),0) -> 0 | H22: =IFERROR(SUM(H23:H49),0) -> 0 | I22: =IFERROR(SUM(I23:I49),0) -> 0 | J22: =IFERROR(SUM(J23:J49),0) -> 0 | K22: =IFERROR(SUM(K23:K49),0) -> 0 | ... AA22: =IFERROR(SUM(AA23:AA49),0) -> 0 | AC22: =IFERROR(SUM(AC23:AC49),0) -> 0 | AD22: =IFERROR(SUM(AD23:AD49),0) -> 0
AC23: =IFERROR(SUM(D23,F23,H23,J23,L23,N23,P23,R23,T23,V23,X23,Z23),0) -> 0 | AD23: =IFERROR(SUM(E23,G23,I23,K23,M23,O23,Q23,S23,U23,W23,Y23,AA23),0) -> 0
AC24: =IFERROR(SUM(D24,F24,H24,J24,L24,N24,P24,R24,T24,V24,X24,Z24),0) -> 0 | AD24: =IFERROR(SUM(E24,G24,I24,K24,M24,O24,Q24,S24,U24,W24,Y24,AA24),0) -> 0
AC25: =IFERROR(SUM(D25,F25,H25,J25,L25,N25,P25,R25,T25,V25,X25,Z25),0) -> 0 | AD25: =IFERROR(SUM(E25,G25,I25,K25,M25,O25,Q25,S25,U25,W25,Y25,AA25),0) -> 0
AC26: =IFERROR(SUM(D26,F26,H26,J26,L26,N26,P26,R26,T26,V26,X26,Z26),0) -> 0 | AD26: =IFERROR(SUM(E26,G26,I26,K26,M26,O26,Q26,S26,U26,W26,Y26,AA26),0) -> 0
AC27: =IFERROR(SUM(D27,F27,H27,J27,L27,N27,P27,R27,T27,V27,X27,Z27),0) -> 0 | AD27: =IFERROR(SUM(E27,G27,I27,K27,M27,O27,Q27,S27,U27,W27,Y27,AA27),0) -> 0
AC28: =IFERROR(SUM(D28,F28,H28,J28,L28,N28,P28,R28,T28,V28,X28,Z28),0) -> 0 | AD28: =IFERROR(SUM(E28,G28,I28,K28,M28,O28,Q28,S28,U28,W28,Y28,AA28),0) -> 0
AC29: =IFERROR(SUM(D29,F29,H29,J29,L29,N29,P29,R29,T29,V29,X29,Z29),0) -> 0 | AD29: =IFERROR(SUM(E29,G29,I29,K29,M29,O29,Q29,S29,U29,W29,Y29,AA29),0) -> 0
AC30: =IFERROR(SUM(D30,F30,H30,J30,L30,N30,P30,R30,T30,V30,X30,Z30),0) -> 0 | AD30: =IFERROR(SUM(E30,G30,I30,K30,M30,O30,Q30,S30,U30,W30,Y30,AA30),0) -> 0
AC31: =IFERROR(SUM(D31,F31,H31,J31,L31,N31,P31,R31,T31,V31,X31,Z31),0) -> 0 | AD31: =IFERROR(SUM(E31,G31,I31,K31,M31,O31,Q31,S31,U31,W31,Y31,AA31),0) -> 0
AC32: =IFERROR(SUM(D32,F32,H32,J32,L32,N32,P32,R32,T32,V32,X32,Z32),0) -> 0 | AD32: =IFERROR(SUM(E32,G32,I32,K32,M32,O32,Q32,S32,U32,W32,Y32,AA32),0) -> 0
AC33: =IFERROR(SUM(D33,F33,H33,J33,L33,N33,P33,R33,T33,V33,X33,Z33),0) -> 0 | AD33: =IFERROR(SUM(E33,G33,I33,K33,M33,O33,Q33,S33,U33,W33,Y33,AA33),0) -> 0
AC34: =IFERROR(SUM(D34,F34,H34,J34,L34,N34,P34,R34,T34,V34,X34,Z34),0) -> 0 | AD34: =IFERROR(SUM(E34,G34,I34,K34,M34,O34,Q34,S34,U34,W34,Y34,AA34),0) -> 0
... AC49: =IFERROR(SUM(D49,F49,H49,J49,L49,N49,P49,R49,T49,V49,X49,Z49),0) -> 0 | AD49: =IFERROR(SUM(E49,G49,I49,K49,M49,O49,Q49,S49,U49,W49,Y49,AA49),0) -> 0
C51: OUTRAS RECEITAS
C53: DESCRIÇÃO | D53: JAN | F53: FEV | H53: MAR | J53: ABR | L53: MAI | N53: JUN | P53: JUL | R53: AGO | T53: SET | V53: OUT | X53: NOV | Z53: DEZ | AC53: SOMATÓRIO
D54: PREVISTO | E54: REALIZADO | F54: PREVISTO | G54: REALIZADO | H54: PREVISTO | I54: REALIZADO | J54: PREVISTO | K54: REALIZADO | L54: PREVISTO | M54: REALIZADO | N54: PREVISTO | O54: REALIZADO | P54: PREVISTO | Q54: REALIZADO | R54: PREVISTO | S54: REALIZADO | T54: PREVISTO | U54: REALIZADO | V54: PREVISTO | W54: REALIZADO | X54: PREVISTO | Y54: REALIZADO | Z54: PREVISTO | AA54: REALIZADO | AC54: PREVISTO | AD54: REALIZADO
D55: =IFERROR(SUM(D56:D69),0) -> 0 | E55: =IFERROR(SUM(E56:E69),0) -> 0 | F55: =IFERROR(SUM(F56:F69),0) -> 0 | G55: =IFERROR(SUM(G56:G69),0) -> 0 | H55: =IFERROR(SUM(H56:H69),0) -> 0 | I55: =IFERROR(SUM(I56:I69),0) -> 0 | J55: =IFERROR(SUM(J56:J69),0) -> 0 | K55: =IFERROR(SUM(K56:K69),0) -> 0 | ... AA55: =IFERROR(SUM(AA56:AA69),0) -> 0 | AC55: =IFERROR(SUM(AC56:AC69),0) -> 0 | AD55: =IFERROR(SUM(AD56:AD69),0) -> 0
AC56: =IFERROR(SUM(D56,F56,H56,J56,L56,N56,P56,R56,T56,V56,X56,Z56),0) -> 0 | AD56: =IFERROR(SUM(E56,G56,I56,K56,M56,O56,Q56,S56,U56,W56,Y56,AA56),0) -> 0
AC57: =IFERROR(SUM(D57,F57,H57,J57,L57,N57,P57,R57,T57,V57,X57,Z57),0) -> 0 | AD57: =IFERROR(SUM(E57,G57,I57,K57,M57,O57,Q57,S57,U57,W57,Y57,AA57),0) -> 0
AC58: =IFERROR(SUM(D58,F58,H58,J58,L58,N58,P58,R58,T58,V58,X58,Z58),0) -> 0 | AD58: =IFERROR(SUM(E58,G58,I58,K58,M58,O58,Q58,S58,U58,W58,Y58,AA58),0) -> 0
AC59: =IFERROR(SUM(D59,F59,H59,J59,L59,N59,P59,R59,T59,V59,X59,Z59),0) -> 0 | AD59: =IFERROR(SUM(E59,G59,I59,K59,M59,O59,Q59,S59,U59,W59,Y59,AA59),0) -> 0
AC60: =IFERROR(SUM(D60,F60,H60,J60,L60,N60,P60,R60,T60,V60,X60,Z60),0) -> 0 | AD60: =IFERROR(SUM(E60,G60,I60,K60,M60,O60,Q60,S60,U60,W60,Y60,AA60),0) -> 0
AC61: =IFERROR(SUM(D61,F61,H61,J61,L61,N61,P61,R61,T61,V61,X61,Z61),0) -> 0 | AD61: =IFERROR(SUM(E61,G61,I61,K61,M61,O61,Q61,S61,U61,W61,Y61,AA61),0) -> 0
AC62: =IFERROR(SUM(D62,F62,H62,J62,L62,N62,P62,R62,T62,V62,X62,Z62),0) -> 0 | AD62: =IFERROR(SUM(E62,G62,I62,K62,M62,O62,Q62,S62,U62,W62,Y62,AA62),0) -> 0
AC63: =IFERROR(SUM(D63,F63,H63,J63,L63,N63,P63,R63,T63,V63,X63,Z63),0) -> 0 | AD63: =IFERROR(SUM(E63,G63,I63,K63,M63,O63,Q63,S63,U63,W63,Y63,AA63),0) -> 0
AC64: =IFERROR(SUM(D64,F64,H64,J64,L64,N64,P64,R64,T64,V64,X64,Z64),0) -> 0 | AD64: =IFERROR(SUM(E64,G64,I64,K64,M64,O64,Q64,S64,U64,W64,Y64,AA64),0) -> 0
AC65: =IFERROR(SUM(D65,F65,H65,J65,L65,N65,P65,R65,T65,V65,X65,Z65),0) -> 0 | AD65: =IFERROR(SUM(E65,G65,I65,K65,M65,O65,Q65,S65,U65,W65,Y65,AA65),0) -> 0
AC66: =IFERROR(SUM(D66,F66,H66,J66,L66,N66,P66,R66,T66,V66,X66,Z66),0) -> 0 | AD66: =IFERROR(SUM(E66,G66,I66,K66,M66,O66,Q66,S66,U66,W66,Y66,AA66),0) -> 0
AC67: =IFERROR(SUM(D67,F67,H67,J67,L67,N67,P67,R67,T67,V67,X67,Z67),0) -> 0 | AD67: =IFERROR(SUM(E67,G67,I67,K67,M67,O67,Q67,S67,U67,W67,Y67,AA67),0) -> 0
... AC69: =IFERROR(SUM(D69,F69,H69,J69,L69,N69,P69,R69,T69,V69,X69,Z69),0) -> 0 | AD69: =IFERROR(SUM(E69,G69,I69,K69,M69,O69,Q69,S69,U69,W69,Y69,AA69),0) -> 0
C71: RECEITAS FINANCEIRAS
C73: DESCRIÇÃO | D73: JAN | F73: FEV | H73: MAR | J73: ABR | L73: MAI | N73: JUN | P73: JUL | R73: AGO | T73: SET | V73: OUT | X73: NOV | Z73: DEZ | AC73: SOMATÓRIO
D74: PREVISTO | E74: REALIZADO | F74: PREVISTO | G74: REALIZADO | H74: PREVISTO | I74: REALIZADO | J74: PREVISTO | K74: REALIZADO | L74: PREVISTO | M74: REALIZADO | N74: PREVISTO | O74: REALIZADO | P74: PREVISTO | Q74: REALIZADO | R74: PREVISTO | S74: REALIZADO | T74: PREVISTO | U74: REALIZADO | V74: PREVISTO | W74: REALIZADO | X74: PREVISTO | Y74: REALIZADO | Z74: PREVISTO | AA74: REALIZADO | AC74: PREVISTO | AD74: REALIZADO
D75: =IFERROR(SUM(D76:D85),0) -> 0 | E75: =IFERROR(SUM(E76:E85),0) -> 0 | F75: =IFERROR(SUM(F76:F85),0) -> 0 | G75: =IFERROR(SUM(G76:G85),0) -> 0 | H75: =IFERROR(SUM(H76:H85),0) -> 0 | I75: =IFERROR(SUM(I76:I85),0) -> 0 | J75: =IFERROR(SUM(J76:J85),0) -> 0 | K75: =IFERROR(SUM(K76:K85),0) -> 0 | ... AA75: =IFERROR(SUM(AA76:AA85),0) -> 0 | AC75: =IFERROR(SUM(AC76:AC85),0) -> 0 | AD75: =IFERROR(SUM(AD76:AD85),0) -> 0
AC76: =IFERROR(SUM(D76,F76,H76,J76,L76,N76,P76,R76,T76,V76,X76,Z76),0) -> 0 | AD76: =IFERROR(SUM(E76,G76,I76,K76,M76,O76,Q76,S76,U76,W76,Y76,AA76),0) -> 0
AC77: =IFERROR(SUM(D77,F77,H77,J77,L77,N77,P77,R77,T77,V77,X77,Z77),0) -> 0 | AD77: =IFERROR(SUM(E77,G77,I77,K77,M77,O77,Q77,S77,U77,W77,Y77,AA77),0) -> 0
AC78: =IFERROR(SUM(D78,F78,H78,J78,L78,N78,P78,R78,T78,V78,X78,Z78),0) -> 0 | AD78: =IFERROR(SUM(E78,G78,I78,K78,M78,O78,Q78,S78,U78,W78,Y78,AA78),0) -> 0
AC79: =IFERROR(SUM(D79,F79,H79,J79,L79,N79,P79,R79,T79,V79,X79,Z79),0) -> 0 | AD79: =IFERROR(SUM(E79,G79,I79,K79,M79,O79,Q79,S79,U79,W79,Y79,AA79),0) -> 0
AC80: =IFERROR(SUM(D80,F80,H80,J80,L80,N80,P80,R80,T80,V80,X80,Z80),0) -> 0 | AD80: =IFERROR(SUM(E80,G80,I80,K80,M80,O80,Q80,S80,U80,W80,Y80,AA80),0) -> 0
AC81: =IFERROR(SUM(D81,F81,H81,J81,L81,N81,P81,R81,T81,V81,X81,Z81),0) -> 0 | AD81: =IFERROR(SUM(E81,G81,I81,K81,M81,O81,Q81,S81,U81,W81,Y81,AA81),0) -> 0
AC82: =IFERROR(SUM(D82,F82,H82,J82,L82,N82,P82,R82,T82,V82,X82,Z82),0) -> 0 | AD82: =IFERROR(SUM(E82,G82,I82,K82,M82,O82,Q82,S82,U82,W82,Y82,AA82),0) -> 0
AC83: =IFERROR(SUM(D83,F83,H83,J83,L83,N83,P83,R83,T83,V83,X83,Z83),0) -> 0 | AD83: =IFERROR(SUM(E83,G83,I83,K83,M83,O83,Q83,S83,U83,W83,Y83,AA83),0) -> 0
AC84: =IFERROR(SUM(D84,F84,H84,J84,L84,N84,P84,R84,T84,V84,X84,Z84),0) -> 0 | AD84: =IFERROR(SUM(E84,G84,I84,K84,M84,O84,Q84,S84,U84,W84,Y84,AA84),0) -> 0
AC85: =IFERROR(SUM(D85,F85,H85,J85,L85,N85,P85,R85,T85,V85,X85,Z85),0) -> 0 | AD85: =IFERROR(SUM(E85,G85,I85,K85,M85,O85,Q85,S85,U85,W85,Y85,AA85),0) -> 0
C88: Esta obra está licenciada com uma Licença Creative Commons Atribuição-NãoComercial 4.0 Internacional.

Sheet GASTOS
D2: REGISTRO FINANCEIRO MENSAL | AB2: Código
AB3: R.OP.007
AB4: Revisão
AB5: 1.0
AB6: Data
AB7: 45763
AB8: Página
AB9: RECEITAS / R.OP.007
C12: GASTOS
E14: JAN | G14: FEV | I14: MAR | K14: ABR | M14: MAI | O14: JUN | Q14: JUL | S14: AGO | U14: SET | W14: OUT | Y14: NOV | AA14: DEZ | AD14: SOMATÓRIO
E15: PREVISTO | F15: REALIZADO | G15: PREVISTO | H15: REALIZADO | I15: PREVISTO | J15: REALIZADO | K15: PREVISTO | L15: REALIZADO | M15: PREVISTO | N15: REALIZADO | O15: PREVISTO | P15: REALIZADO | Q15: PREVISTO | R15: REALIZADO | S15: PREVISTO | T15: REALIZADO | U15: PREVISTO | V15: REALIZADO | W15: PREVISTO | X15: REALIZADO | Y15: PREVISTO | Z15: REALIZADO | AA15: PREVISTO | AB15: REALIZADO | AD15: PREVISTO | AE15: REALIZADO
C16: TOTAL MENSAL | E16: =IFERROR(SUM(E22,E88,E145,E114),0) -> 0 | F16: =IFERROR(SUM(F22,F88,F145,F114),0) -> 0 | G16: =IFERROR(SUM(G22,G88,G145,G114),0) -> 0 | H16: =IFERROR(SUM(H22,H88,H145,H114),0) -> 0 | I16: =IFERROR(SUM(I22,I88,I145,I114),0) -> 0 | J16: =IFERROR(SUM(J22,J88,J145,J114),0) -> 0 | K16: =IFERROR(SUM(K22,K88,K145,K114),0) -> 0 | L16: =IFERROR(SUM(L22,L88,L145,L114),0) -> 0 | ... AB16: =IFERROR(SUM(AB22,AB88,AB145,AB114),0) -> 0 | AD16: =IFERROR(SUM(E16,G16,I16,K16,M16,O16,Q16,S16,U16,W16,Y16,AA16),0) -> 0 | AE16: =IFERROR(SUM(F16,H16,J16,L16,N16,P16,R16,T16,V16,X16,Z16,AB16),0) -> 0
C18: DESPESAS OPERACIONAIS
C20: SUBCATEGORIA | D20: DESCRIÇÃO | E20: JAN | G20: FEV | I20: MAR | K20: ABR | M20: MAI | O20: JUN | Q20: JUL | S20: AGO | U20: SET | W20: OUT | Y20: NOV | AA20: DEZ | AD20: SOMATÓRIO
E21: PREVISTO | F21: REALIZADO | G21: PREVISTO | H21: REALIZADO | I21: PREVISTO | J21: REALIZADO | K21: PREVISTO | L21: REALIZADO | M21: PREVISTO | N21: REALIZADO | O21: PREVISTO | P21: REALIZADO | Q21: PREVISTO | R21: REALIZADO | S21: PREVISTO | T21: REALIZADO | U21: PREVISTO | V21: REALIZADO | W21: PREVISTO | X21: REALIZADO | Y21: PREVISTO | Z21: REALIZADO | AA21: PREVISTO | AB21: REALIZADO | AD21: PREVISTO | AE21: REALIZADO
E22: =IFERROR(SUM(E23:E82),0) -> 0 | F22: =IFERROR(SUM(F23:F82),0) -> 0 | G22: =IFERROR(SUM(G23:G82),0) -> 0 | H22: =IFERROR(SUM(H23:H82),0) -> 0 | I22: =IFERROR(SUM(I23:I82),0) -> 0 | J22: =IFERROR(SUM(J23:J82),0) -> 0 | K22: =IFERROR(SUM(K23:K82),0) -> 0 | L22: =IFERROR(SUM(L23:L82),0) -> 0 | ... AB22: =IFERROR(SUM(AB23:AB82),0) -> 0 | AD22: =IFERROR(SUM(AD23:AD82),0) -> 0 | AE22: =IFERROR(SUM(AE23:AE82),0) -> 0
AD23: =IFERROR(SUM(E23,G23,I23,K23,M23,O23,Q23,S23,U23,W23,Y23,AA23),0) -> 0 | AE23: =IFERROR(SUM(F23,H23,J23,L23,N23,P23,R23,T23,V23,X23,Z23,AB23),0) -> 0
AD24: =IFERROR(SUM(E24,G24,I24,K24,M24,O24,Q24,S24,U24,W24,Y24,AA24),0) -> 0 | AE24: =IFERROR(SUM(F24,H24,J24,L24,N24,P24,R24,T24,V24,X24,Z24,AB24),0) -> 0
AD25: =IFERROR(SUM(E25,G25,I25,K25,M25,O25,Q25,S25,U25,W25,Y25,AA25),0) -> 0 | AE25: =IFERROR(SUM(F25,H25,J25,L25,N25,P25,R25,T25,V25,X25,Z25,AB25),0) -> 0
AD26: =IFERROR(SUM(E26,G26,I26,K26,M26,O26,Q26,S26,U26,W26,Y26,AA26),0) -> 0 | AE26: =IFERROR(SUM(F26,H26,J26,L26,N26,P26,R26,T26,V26,X26,Z26,AB26),0) -> 0
AD27: =IFERROR(SUM(E27,G27,I27,K27,M27,O27,Q27,S27,U27,W27,Y27,AA27),0) -> 0 | AE27: =IFERROR(SUM(F27,H27,J27,L27,N27,P27,R27,T27,V27,X27,Z27,AB27),0) -> 0
AD28: =IFERROR(SUM(E28,G28,I28,K28,M28,O28,Q28,S28,U28,W28,Y28,AA28),0) -> 0 | AE28: =IFERROR(SUM(F28,H28,J28,L28,N28,P28,R28,T28,V28,X28,Z28,AB28),0) -> 0
AD29: =IFERROR(SUM(E29,G29,I29,K29,M29,O29,Q29,S29,U29,W29,Y29,AA29),0) -> 0 | AE29: =IFERROR(SUM(F29,H29,J29,L29,N29,P29,R29,T29,V29,X29,Z29,AB29),0) -> 0
AD30: =IFERROR(SUM(E30,G30,I30,K30,M30,O30,Q30,S30,U30,W30,Y30,AA30),0) -> 0 | AE30: =IFERROR(SUM(F30,H30,J30,L30,N30,P30,R30,T30,V30,X30,Z30,AB30),0) -> 0
AD31: =IFERROR(SUM(E31,G31,I31,K31,M31,O31,Q31,S31,U31,W31,Y31,AA31),0) -> 0 | AE31: =IFERROR(SUM(F31,H31,J31,L31,N31,P31,R31,T31,V31,X31,Z31,AB31),0) -> 0
AD32: =IFERROR(SUM(E32,G32,I32,K32,M32,O32,Q32,S32,U32,W32,Y32,AA32),0) -> 0 | AE32: =IFERROR(SUM(F32,H32,J32,L32,N32,P32,R32,T32,V32,X32,Z32,AB32),0) -> 0
AD33: =IFERROR(SUM(E33,G33,I33,K33,M33,O33,Q33,S33,U33,W33,Y33,AA33),0) -> 0 | AE33: =IFERROR(SUM(F33,H33,J33,L33,N33,P33,R33,T33,V33,X33,Z33,AB33),0) -> 0
AD34: =IFERROR(SUM(E34,G34,I34,K34,M34,O34,Q34,S34,U34,W34,Y34,AA34),0) -> 0 | AE34: =IFERROR(SUM(F34,H34,J34,L34,N34,P34,R34,T34,V34,X34,Z34,AB34),0) -> 0
... AD82: =IFERROR(SUM(E82,G82,I82,K82,M82,O82,Q82,S82,U82,W82,Y82,AA82),0) -> 0 | AE82: =IFERROR(SUM(F82,H82,J82,L82,N82,P82,R82,T82,V82,X82,Z82,AB82),0) -> 0
C84: CUSTOS PRODUTOS/SERVIÇOS
C86: SUBCATEGORIA | D86: DESCRIÇÃO | E86: JAN | G86: FEV | I86: MAR | K86: ABR | M86: MAI | O86: JUN | Q86: JUL | S86: AGO | U86: SET | W86: OUT | Y86: NOV | AA86: DEZ | AD86: SOMATÓRIO
E87: PREVISTO | F87: REALIZADO | G87: PREVISTO | H87: REALIZADO | I87: PREVISTO | J87: REALIZADO | K87: PREVISTO | L87: REALIZADO | M87: PREVISTO | N87: REALIZADO | O87: PREVISTO | P87: REALIZADO | Q87: PREVISTO | R87: REALIZADO | S87: PREVISTO | T87: REALIZADO | U87: PREVISTO | V87: REALIZADO | W87: PREVISTO | X87: REALIZADO | Y87: PREVISTO | Z87: REALIZADO | AA87: PREVISTO | AB87: REALIZADO | AD87: PREVISTO | AE87: REALIZADO
E88: =IFERROR(SUM(E89:E108),0) -> 0 | F88: =IFERROR(SUM(F89:F108),0) -> 0 | G88: =IFERROR(SUM(G89:G108),0) -> 0 | H88: =IFERROR(SUM(H89:H108),0) -> 0 | I88: =IFERROR(SUM(I89:I108),0) -> 0 | J88: =IFERROR(SUM(J89:J108),0) -> 0 | K88: =IFERROR(SUM(K89:K108),0) -> 0 | L88: =IFERROR(SUM(L89:L108),0) -> 0 | ... AB88: =IFERROR(SUM(AB89:AB108),0) -> 0 | AD88: =IFERROR(SUM(AD89:AD108),0) -> 0 | AE88: =IFERROR(SUM(AE89:AE108),0) -> 0
AD89: =IFERROR(SUM(E89,G89,I89,K89,M89,O89,Q89,S89,U89,W89,Y89,AA89),0) -> 0 | AE89: =IFERROR(SUM(F89,H89,J89,L89,N89,P89,R89,T89,V89,X89,Z89,AB89),0) -> 0
AD90: =IFERROR(SUM(E90,G90,I90,K90,M90,O90,Q90,S90,U90,W90,Y90,AA90),0) -> 0 | AE90: =IFERROR(SUM(F90,H90,J90,L90,N90,P90,R90,T90,V90,X90,Z90,AB90),0) -> 0
AD91: =IFERROR(SUM(E91,G91,I91,K91,M91,O91,Q91,S91,U91,W91,Y91,AA91),0) -> 0 | AE91: =IFERROR(SUM(F91,H91,J91,L91,N91,P91,R91,T91,V91,X91,Z91,AB91),0) -> 0
AD92: =IFERROR(SUM(E92,G92,I92,K92,M92,O92,Q92,S92,U92,W92,Y92,AA92),0) -> 0 | AE92: =IFERROR(SUM(F92,H92,J92,L92,N92,P92,R92,T92,V92,X92,Z92,AB92),0) -> 0
AD93: =IFERROR(SUM(E93,G93,I93,K93,M93,O93,Q93,S93,U93,W93,Y93,AA93),0) -> 0 | AE93: =IFERROR(SUM(F93,H93,J93,L93,N93,P93,R93,T93,V93,X93,Z93,AB93),0) -> 0
AD94: =IFERROR(SUM(E94,G94,I94,K94,M94,O94,Q94,S94,U94,W94,Y94,AA94),0) -> 0 | AE94: =IFERROR(SUM(F94,H94,J94,L94,N94,P94,R94,T94,V94,X94,Z94,AB94),0) -> 0
AD95: =IFERROR(SUM(E95,G95,I95,K95,M95,O95,Q95,S95,U95,W95,Y95,AA95),0) -> 0 | AE95: =IFERROR(SUM(F95,H95,J95,L95,N95,P95,R95,T95,V95,X95,Z95,AB95),0) -> 0
AD96: =IFERROR(SUM(E96,G96,I96,K96,M96,O96,Q96,S96,U96,W96,Y96,AA96),0) -> 0 | AE96: =IFERROR(SUM(F96,H96,J96,L96,N96,P96,R96,T96,V96,X96,Z96,AB96),0) -> 0
AD97: =IFERROR(SUM(E97,G97,I97,K97,M97,O97,Q97,S97,U97,W97,Y97,AA97),0) -> 0 | AE97: =IFERROR(SUM(F97,H97,J97,L97,N97,P97,R97,T97,V97,X97,Z97,AB97),0) -> 0
AD98: =IFERROR(SUM(E98,G98,I98,K98,M98,O98,Q98,S98,U98,W98,Y98,AA98),0) -> 0 | AE98: =IFERROR(SUM(F98,H98,J98,L98,N98,P98,R98,T98,V98,X98,Z98,AB98),0) -> 0
AD99: =IFERROR(SUM(E99,G99,I99,K99,M99,O99,Q99,S99,U99,W99,Y99,AA99),0) -> 0 | AE99: =IFERROR(SUM(F99,H99,J99,L99,N99,P99,R99,T99,V99,X99,Z99,AB99),0) -> 0
AD100: =IFERROR(SUM(E100,G100,I100,K100,M100,O100,Q100,S100,U100,W100,Y100,AA100),0) -> 0 | AE100: =IFERROR(SUM(F100,H100,J100,L100,N100,P100,R100,T100,V100,X100,Z100,AB100),0) -> 0
... AD108: =IFERROR(SUM(E108,G108,I108,K108,M108,O108,Q108,S108,U108,W108,Y108,AA108),0) -> 0 | AE108: =IFERROR(SUM(F108,H108,J108,L108,N108,P108,R108,T108,V108,X108,Z108,AB108),0) -> 0
C110: IMPOSTOS E TAXAS
C112: SUBCATEGORIA | D112: DESCRIÇÃO | E112: JAN | G112: FEV | I112: MAR | K112: ABR | M112: MAI | O112: JUN | Q112: JUL | S112: AGO | U112: SET | W112: OUT | Y112: NOV | AA112: DEZ | AD112: SOMATÓRIO
E113: PREVISTO | F113: REALIZADO | G113: PREVISTO | H113: REALIZADO | I113: PREVISTO | J113: REALIZADO | K113: PREVISTO | L113: REALIZADO | M113: PREVISTO | N113: REALIZADO | O113: PREVISTO | P113: REALIZADO | Q113: PREVISTO | R113: REALIZADO | S113: PREVISTO | T113: REALIZADO | U113: PREVISTO | V113: REALIZADO | W113: PREVISTO | X113: REALIZADO | Y113: PREVISTO | Z113: REALIZADO | AA113: PREVISTO | AB113: REALIZADO | AD113: PREVISTO | AE113: REALIZADO
E114: =IFERROR(SUM(E115:E139),0) -> 0 | F114: =IFERROR(SUM(F115:F139),0) -> 0 | G114: =IFERROR(SUM(G115:G139),0) -> 0 | H114: =IFERROR(SUM(H115:H139),0) -> 0 | I114: =IFERROR(SUM(I115:I139),0) -> 0 | J114: =IFERROR(SUM(J115:J139),0) -> 0 | K114: =IFERROR(SUM(K115:K139),0) -> 0 | L114: =IFERROR(SUM(L115:L139),0) -> 0 | ... AB114: =IFERROR(SUM(AB115:AB139),0) -> 0 | AD114: =IFERROR(SUM(AD115:AD139),0) -> 0 | AE114: =IFERROR(SUM(AE115:AE139),0) -> 0
AD115: =IFERROR(SUM(E115,G115,I115,K115,M115,O115,Q115,S115,U115,W115,Y115,AA115),0) -> 0 | AE115: =IFERROR(SUM(F115,H115,J115,L115,N115,P115,R115,T115,V115,X115,Z115,AB115),0) -> 0
AD116: =IFERROR(SUM(E116,G116,I116,K116,M116,O116,Q116,S116,U116,W116,Y116,AA116),0) -> 0 | AE116: =IFERROR(SUM(F116,H116,J116,L116,N116,P116,R116,T116,V116,X116,Z116,AB116),0) -> 0
AD117: =IFERROR(SUM(E117,G117,I117,K117,M117,O117,Q117,S117,U117,W117,Y117,AA117),0) -> 0 | AE117: =IFERROR(SUM(F117,H117,J117,L117,N117,P117,R117,T117,V117,X117,Z117,AB117),0) -> 0
AD118: =IFERROR(SUM(E118,G118,I118,K118,M118,O118,Q118,S118,U118,W118,Y118,AA118),0) -> 0 | AE118: =IFERROR(SUM(F118,H118,J118,L118,N118,P118,R118,T118,V118,X118,Z118,AB118),0) -> 0
AD119: =IFERROR(SUM(E119,G119,I119,K119,M119,O119,Q119,S119,U119,W119,Y119,AA119),0) -> 0 | AE119: =IFERROR(SUM(F119,H119,J119,L119,N119,P119,R119,T119,V119,X119,Z119,AB119),0) -> 0
AD120: =IFERROR(SUM(E120,G120,I120,K120,M120,O120,Q120,S120,U120,W120,Y120,AA120),0) -> 0 | AE120: =IFERROR(SUM(F120,H120,J120,L120,N120,P120,R120,T120,V120,X120,Z120,AB120),0) -> 0
AD121: =IFERROR(SUM(E121,G121,I121,K121,M121,O121,Q121,S121,U121,W121,Y121,AA121),0) -> 0 | AE121: =IFERROR(SUM(F121,H121,J121,L121,N121,P121,R121,T121,V121,X121,Z121,AB121),0) -> 0
AD122: =IFERROR(SUM(E122,G122,I122,K122,M122,O122,Q122,S122,U122,W122,Y122,AA122),0) -> 0 | AE122: =IFERROR(SUM(F122,H122,J122,L122,N122,P122,R122,T122,V122,X122,Z122,AB122),0) -> 0
AD123: =IFERROR(SUM(E123,G123,I123,K123,M123,O123,Q123,S123,U123,W123,Y123,AA123),0) -> 0 | AE123: =IFERROR(SUM(F123,H123,J123,L123,N123,P123,R123,T123,V123,X123,Z123,AB123),0) -> 0
AD124: =IFERROR(SUM(E124,G124,I124,K124,M124,O124,Q124,S124,U124,W124,Y124,AA124),0) -> 0 | AE124: =IFERROR(SUM(F124,H124,J124,L124,N124,P124,R124,T124,V124,X124,Z124,AB124),0) -> 0
AD125: =IFERROR(SUM(E125,G125,I125,K125,M125,O125,Q125,S125,U125,W125,Y125,AA125),0) -> 0 | AE125: =IFERROR(SUM(F125,H125,J125,L125,N125,P125,R125,T125,V125,X125,Z125,AB125),0) -> 0
AD126: =IFERROR(SUM(E126,G126,I126,K126,M126,O126,Q126,S126,U126,W126,Y126,AA126),0) -> 0 | AE126: =IFERROR(SUM(F126,H126,J126,L126,N126,P126,R126,T126,V126,X126,Z126,AB126),0) -> 0
... AD139: =IFERROR(SUM(E139,G139,I139,K139,M139,O139,Q139,S139,U139,W139,Y139,AA139),0) -> 0 | AE139: =IFERROR(SUM(F139,H139,J139,L139,N139,P139,R139,T139,V139,X139,Z139,AB139),0) -> 0
C141: INVESTIMENTOS
C143: SUBCATEGORIA | D143: DESCRIÇÃO | E143: JAN | G143: FEV | I143: MAR | K143: ABR | M143: MAI | O143: JUN | Q143: JUL | S143: AGO | U143: SET | W143: OUT | Y143: NOV | AA143: DEZ | AD143: SOMATÓRIO
E144: PREVISTO | F144: REALIZADO | G144: PREVISTO | H144: REALIZADO | I144: PREVISTO | J144: REALIZADO | K144: PREVISTO | L144: REALIZADO | M144: PREVISTO | N144: REALIZADO | O144: PREVISTO | P144: REALIZADO | Q144: PREVISTO | R144: REALIZADO | S144: PREVISTO | T144: REALIZADO | U144: PREVISTO | V144: REALIZADO | W144: PREVISTO | X144: REALIZADO | Y144: PREVISTO | Z144: REALIZADO | AA144: PREVISTO | AB144: REALIZADO | AD144: PREVISTO | AE144: REALIZADO
E145: =IFERROR(SUM(E146:E155),0) -> 0 | F145: =IFERROR(SUM(F146:F155),0) -> 0 | G145: =IFERROR(SUM(G146:G155),0) -> 0 | H145: =IFERROR(SUM(H146:H155),0) -> 0 | I145: =IFERROR(SUM(I146:I155),0) -> 0 | J145: =IFERROR(SUM(J146:J155),0) -> 0 | K145: =IFERROR(SUM(K146:K155),0) -> 0 | L145: =IFERROR(SUM(L146:L155),0) -> 0 | ... AB145: =IFERROR(SUM(AB146:AB155),0) -> 0 | AD145: =IFERROR(SUM(AD146:AD155),0) -> 0 | AE145: =IFERROR(SUM(AE146:AE155),0) -> 0
AD146: =IFERROR(SUM(E146,G146,I146,K146,M146,O146,Q146,S146,U146,W146,Y146,AA146),0) -> 0 | AE146: =IFERROR(SUM(F146,H146,J146,L146,N146,P146,R146,T146,V146,X146,Z146,AB146),0) -> 0
AD147: =IFERROR(SUM(E147,G147,I147,K147,M147,O147,Q147,S147,U147,W147,Y147,AA147),0) -> 0 | AE147: =IFERROR(SUM(F147,H147,J147,L147,N147,P147,R147,T147,V147,X147,Z147,AB147),0) -> 0
AD148: =IFERROR(SUM(E148,G148,I148,K148,M148,O148,Q148,S148,U148,W148,Y148,AA148),0) -> 0 | AE148: =IFERROR(SUM(F148,H148,J148,L148,N148,P148,R148,T148,V148,X148,Z148,AB148),0) -> 0
AD149: =IFERROR(SUM(E149,G149,I149,K149,M149,O149,Q149,S149,U149,W149,Y149,AA149),0) -> 0 | AE149: =IFERROR(SUM(F149,H149,J149,L149,N149,P149,R149,T149,V149,X149,Z149,AB149),0) -> 0
AD150: =IFERROR(SUM(E150,G150,I150,K150,M150,O150,Q150,S150,U150,W150,Y150,AA150),0) -> 0 | AE150: =IFERROR(SUM(F150,H150,J150,L150,N150,P150,R150,T150,V150,X150,Z150,AB150),0) -> 0
AD151: =IFERROR(SUM(E151,G151,I151,K151,M151,O151,Q151,S151,U151,W151,Y151,AA151),0) -> 0 | AE151: =IFERROR(SUM(F151,H151,J151,L151,N151,P151,R151,T151,V151,X151,Z151,AB151),0) -> 0
AD152: =IFERROR(SUM(E152,G152,I152,K152,M152,O152,Q152,S152,U152,W152,Y152,AA152),0) -> 0 | AE152: =IFERROR(SUM(F152,H152,J152,L152,N152,P152,R152,T152,V152,X152,Z152,AB152),0) -> 0
AD153: =IFERROR(SUM(E153,G153,I153,K153,M153,O153,Q153,S153,U153,W153,Y153,AA153),0) -> 0 | AE153: =IFERROR(SUM(F153,H153,J153,L153,N153,P153,R153,T153,V153,X153,Z153,AB153),0) -> 0
AD154: =IFERROR(SUM(E154,G154,I154,K154,M154,O154,Q154,S154,U154,W154,Y154,AA154),0) -> 0 | AE154: =IFERROR(SUM(F154,H154,J154,L154,N154,P154,R154,T154,V154,X154,Z154,AB154),0) -> 0
AD155: =IFERROR(SUM(E155,G155,I155,K155,M155,O155,Q155,S155,U155,W155,Y155,AA155),0) -> 0 | AE155: =IFERROR(SUM(F155,H155,J155,L155,N155,P155,R155,T155,V155,X155,Z155,AB155),0) -> 0
C158: Esta obra está licenciada com uma Licença Creative Commons Atribuição-NãoComercial 4.0 Internacional.

Sheet PLANO DE CONTAS
E2: PLANO DE CONTAS | I2: Código
I3: R.PD.023
I4: Revisão
I5: 2.0
I6: Data
I7: 45513
I8: Página
I9: PLANO DE CONTAS / R.PD.023
B11: PLANO DE CONTAS
C14: RECEITAS
C16: PRODUTOS / SERVIÇOS
C45: OUTRAS RECEITAS
C47: Empréstimos de instituições
C48: Empréstimos de Sócios
C49: Integralização de capital
C50: Reembolso
C51: Outros
C61: RECEITAS FINANCEIRAS
C63: Crédito de Cartão
C64: Juros
C65: Outros
... C75: Esta obra está licenciada com uma Licença Creative Commons Atribuição-NãoComercial 4.0 Internacional.
E79: PLANO DE CONTAS | I79: Código
I81: Revisão
I82: 1.0
I83: Data
I85: Página
B88: PLANO DE CONTAS
C91: DESPESAS
C93: DESPESAS OPERACIONAIS | G93: CUSTO DE PRODUTOS/SERVIÇOS
C95: 13º Salário | G95: Fretes
C96: Adiantamento Salarial | G96: Matéria-prima
C97: Agua | G97: Prestação de Serviços
C98: Aluguel de Equipamentos
C99: Aluguel de Imóveis
C100: Anuidades/Mensalidades
C101: Associação Comercial
C102: Bonificações
C103: Brindes e Doações
C104: Cartório
C105: Coleta de Lixo
C106: Combustíveis e Lubrificantes
C107: Comissões
C108: Correios
C109: Cursos e Treinamentos
... C114: Internet
C115: Lanches e Refeições | G115: IMPOSTOS E TAXAS
C116: Limpeza/Diarista
C117: Manutenção | G117: Alvará
C118: Marketing e Publicidade | G118: Cofins
C119: Material de Limpeza e Conservação | G119: Corpo de Bombeiros
C120: Material Gráfico/Livraria | G120: CSLL
C121: Multas | G121: DARF
C122: PLR - Participação nos Lucros e Resultados | G122: Despesas Bancárias
C123: Pró-Labore | G123: ECAD
C124: Remuneração de Autônomos | G124: FGTS
C125: Remuneração de Estagiários | G125: ICMS
C126: Rescisões | G126: INSS / GPS
C127: Retiradas de Sócios | G127: IOF
C128: Salários | G128: IPI
... C138: Viagens e Hospedagens | G138: Taxa de Prefeitura
C139: Vigilância Patrimonial
G142: INVESTIMENTOS
G144: Aplicações
G145: Aquisição de Imobilizado
G146: Capital de Giro
G147: Empréstimos Bancários
G148: Financiamentos
G149: Investimento Estrutural
G150: Provisionamentos
G151: Reformas
C156: Esta obra está licenciada com uma Licença Creative Commons Atribuição-NãoComercial 4.0 Internacional.

Sheet CONCILIAÇÃO
C2: CONCILIAÇÃO | M2: Código
M3: R.PD.023
M4: Revisão
M5: 2.0
M6: Data
M7: 45513
M8: Página
M9: CONCILIAÇÃO / R.PD.023
B11: AVALIAÇÃO FINANCEIRA
B13: CONTA 01 | C13: jan/23 | D13: fev/23 | E13: mar/23 | F13: abr/23 | G13: mai/23 | H13: jun/23 | I13: jul/23 | J13: ago/23 | K13: set/23 | L13: out/23 | M13: nov/23 | N13: dez/23
B14: SALDO INICIAL:
B15: SALDO FINAL:
B17: CONTA 02 | C17: jan/23 | D17: fev/23 | E17: mar/23 | F17: abr/23 | G17: mai/23 | H17: jun/23 | I17: jul/23 | J17: ago/23 | K17: set/23 | L17: out/23 | M17: nov/23 | N17: dez/23
B18: SALDO INICIAL:
B19: SALDO FINAL:
B21: CAIXA FÍSICO | C21: jan/23 | D21: fev/23 | E21: mar/23 | F21: abr/23 | G21: mai/23 | H21: jun/23 | I21: jul/23 | J21: ago/23 | K21: set/23 | L21: out/23 | M21: nov/23 | N21: dez/23
B22: SALDO INICIAL:
B23: SALDO FINAL:
B25: CONFERÊNCIA | C25: jan/23 | D25: fev/23 | E25: mar/23 | F25: abr/23 | G25: mai/23 | H25: jun/23 | I25: jul/23 | J25: ago/23 | K25: set/23 | L25: out/23 | M25: nov/23 | N25: dez/23
B26: SALDO INICIAL CONTAS | C26: =C14+C18+C22 -> 0 | D26: =D14+D18+D22 -> 0 | E26: =E14+E18+E22 -> 0 | F26: =F14+F18+F22 -> 0 | G26: =G14+G18+G22 -> 0 | H26: =H14+H18+H22 -> 0 | I26: =I14+I18+I22 -> 0 | J26: =J14+J18+J22 -> 0 | ... N26: =N14+N18+N22 -> 0
B27: SALDO FINAL CONTAS | C27: =C15+C19+C23 -> 0 | D27: =D15+D19+D23 -> 0 | E27: =E15+E19+E23 -> 0 | F27: =F15+F19+F23 -> 0 | G27: =G15+G19+G23 -> 0 | H27: =H15+H19+H23 -> 0 | I27: =I15+I19+I23 -> 0 | J27: =J15+J19+J23 -> 0 | ... N27: =N15+N19+N23 -> 0
B28: (+) RECEITAS | C28: =RECEITAS!E16 -> 0 | D28: =RECEITAS!G16 -> 0 | E28: =RECEITAS!I16 -> 0 | F28: =RECEITAS!K16 -> 0 | G28: =RECEITAS!M16 -> 0 | H28: =RECEITAS!O16 -> 0 | I28: =RECEITAS!Q16 -> 0 | J28: =RECEITAS!S16 -> 0 | K28: =RECEITAS!U16 -> 0 | L28: =RECEITAS!W16 -> 0 | M28: =RECEITAS!Y16 -> 0 | N28: =RECEITAS!AA16 -> 0
B29: (-) GASTOS | C29: =GASTOS!F16 -> 0 | D29: =GASTOS!H16 -> 0 | E29: =GASTOS!J16 -> 0 | F29: =GASTOS!L16 -> 0 | G29: =GASTOS!N16 -> 0 | H29: =GASTOS!P16 -> 0 | I29: =GASTOS!R16 -> 0 | J29: =GASTOS!T16 -> 0 | K29: =GASTOS!V16 -> 0 | L29: =GASTOS!X16 -> 0 | M29: =GASTOS!Z16 -> 0 | N29: =GASTOS!AB16 -> 0
B30: GERAÇÃO DE CAIXA EXTRATOS | C30: =C27-C26 -> 0 | D30: =D27-D26 -> 0 | E30: =E27-E26 -> 0 | F30: =F27-F26 -> 0 | G30: =G27-G26 -> 0 | H30: =H27-H26 -> 0 | I30: =I27-I26 -> 0 | J30: =J27-J26 -> 0 | ... N30: =N27-N26 -> 0
B31: GERAÇÃO DE CAIXA PLANILHA | C31: =C28-C29 -> 0 | D31: =D28-D29 -> 0 | E31: =E28-E29 -> 0 | F31: =F28-F29 -> 0 | G31: =G28-G29 -> 0 | H31: =H28-H29 -> 0 | I31: =I28-I29 -> 0 | J31: =J28-J29 -> 0 | ... N31: =N28-N29 -> 0
B32: DIFERENÇA | C32: =C30-C31 -> 0 | D32: =D30-D31 -> 0 | E32: =E30-E31 -> 0 | F32: =F30-F31 -> 0 | G32: =G30-G31 -> 0 | H32: =H30-H31 -> 0 | I32: =I30-I31 -> 0 | J32: =J30-J31 -> 0 | ... N32: =N30-N31 -> 0
C35: This work is licensed under a Creative Commons Attribution-NonCommercial 4.0 International License.
